zoho_crm_mcp/__init__.py
zoho_crm_mcp/config.py
zoho_crm_mcp/server.py
zoho_crm_mcp/zoho_client.py
zoho_crm_mcp_server-0.1.0.dist-info/METADATA
zoho_crm_mcp_server-0.1.0.dist-info/WHEEL
zoho_crm_mcp_server-0.1.0.dist-info/entry_points.txt
zoho_crm_mcp_server-0.1.0.dist-info/licenses/LICENSE
zoho_crm_mcp_server-0.1.0.dist-info/RECORD
