Metadata-Version: 2.4
Name: zoho-crm-mcp-server
Version: 0.1.0
Summary: MCP server for Zoho CRM API integration
Author-email: asklokesh <lokeshmure@live.com>
License-File: LICENSE
Requires-Python: >=3.8
Requires-Dist: mcp>=1.0.0
Requires-Dist: python-dotenv>=0.19.0
Requires-Dist: requests>=2.25.0
Provides-Extra: dev
Requires-Dist: pytest-asyncio>=0.21.0; extra == 'dev'
Requires-Dist: pytest-cov>=4.0; extra == 'dev'
Requires-Dist: pytest>=7.0; extra == 'dev'
Requires-Dist: ruff>=0.1.0; extra == 'dev'
